tyx_schema/__init__.py
tyx_schema/document.py
tyx_schema/settings.py
tyx_schema-0.2.11.dist-info/WHEEL
tyx_schema-0.2.11.dist-info/METADATA
tyx_schema-0.2.11.dist-info/RECORD
