Metadata-Version: 2.3
Name: tyx-schema
Version: 0.2.11
Summary: Safe Pydantic schema for interacting with TyX configurations
Requires-Dist: pydantic>=2.12.3
Requires-Python: >=3.9
